mirabolic/__init__.py
mirabolic/version
mirabolic/cdf/cdf_tools.py
mirabolic/cdf/qq_plot.py
mirabolic/cdf/sample_usage.py
mirabolic/cdf/unit_tests/test_cdf_tools.py
mirabolic/llm_embeddings/llm_embedder.py
mirabolic/llm_embeddings/llm_tools.py
mirabolic/llm_embeddings/test_embed_loop.py
mirabolic/neural_glm/__init__.py
mirabolic/neural_glm/actuarial_loss_functions.py
mirabolic/neural_glm/basic_glm_nn.py
mirabolic/neural_glm/generate_synthetic_data.py
mirabolic/neural_glm/run_examples.py
mirabolic/rates/rate_tools.py
mirabolic-0.3.10.dist-info/LICENSE
mirabolic-0.3.10.dist-info/METADATA
mirabolic-0.3.10.dist-info/WHEEL
mirabolic-0.3.10.dist-info/top_level.txt
mirabolic-0.3.10.dist-info/RECORD
