Metadata-Version: 2.1
Name: mirabolic
Version: 0.3.10
Summary: Statistical and Machine Learning tools from Mirabolic
Home-page: https://github.com/Mirabolic/mirabolic
Download-URL: https://github.com/Mirabolic/mirabolic/archive/refs/tags/v0.3.10.tar.gz
Author: Bill Bradley
License: MIT
Keywords: Statistics,Machine Learning,CDF,Quantiles
Classifier: Development Status :: 3 - Alpha
Classifier: Intended Audience :: Developers
Classifier: Topic :: Scientific/Engineering :: Artificial Intelligence
Classifier: Topic :: Scientific/Engineering :: Mathematics
Classifier: License :: OSI Approved :: MIT License
Classifier: Programming Language :: Python :: 3.9
Classifier: Programming Language :: Python :: 3.10
Classifier: Programming Language :: Python :: 3.11
Classifier: Programming Language :: Python :: 3.12
Classifier: Programming Language :: Python :: 3.13
License-File: LICENSE
Requires-Dist: tensorflow >=2.4.1
Requires-Dist: numpy >=1.19.2
Requires-Dist: scipy >=1.8.0
Requires-Dist: pandas >=1.0.0
Requires-Dist: matplotlib >=3.5.1
Requires-Dist: seaborn >=0.11.2
Requires-Dist: python-dotenv >=1.0.1
Requires-Dist: openai >=0.51.0
Requires-Dist: google-generativeai >=0.7.2
Requires-Dist: huggingface-hub >=0.24.6
Requires-Dist: requests >=2.32.3
Requires-Dist: scikit-learn >=1.5.2
Requires-Dist: umap-learn >=0.5.6
